dmp_cli/__init__.py
dmp_cli/cli.py
dmp_cli-0.1.5.dist-info/DESCRIPTION.rst
dmp_cli-0.1.5.dist-info/METADATA
dmp_cli-0.1.5.dist-info/RECORD
dmp_cli-0.1.5.dist-info/WHEEL
dmp_cli-0.1.5.dist-info/entry_points.txt
dmp_cli-0.1.5.dist-info/metadata.json
dmp_cli-0.1.5.dist-info/top_level.txt
tests/__init__.py
tests/test_dmp_cli.py
